ezconfigparser/__init__.py
ezconfigparser/config.py
ezconfigparser/template.py
ezconfigparser-0.2.8.dist-info/METADATA
ezconfigparser-0.2.8.dist-info/WHEEL
ezconfigparser-0.2.8.dist-info/top_level.txt
ezconfigparser-0.2.8.dist-info/RECORD
